LICENSE
py_lambda_simulator/__init__.py
py_lambda_simulator/http_lambda_simulator.py
py_lambda_simulator/lambda_config.py
py_lambda_simulator/lambda_events.py
py_lambda_simulator/lambda_simulator.py
py_lambda_simulator/sqs_lambda_simulator.py
py_lambda_simulator-0.1.7.dist-info/LICENSE
py_lambda_simulator-0.1.7.dist-info/WHEEL
py_lambda_simulator-0.1.7.dist-info/METADATA
py_lambda_simulator-0.1.7.dist-info/RECORD
