Metadata-Version: 2.1
Name: py-lambda-simulator
Version: 0.1.7
Summary: 
Home-page: https://github.com/hemma/py-lambda-simulator
License: MIT
Author: Johan Bothin
Requires-Python: >=3.8,<4.0
Classifier: License :: OSI Approved :: MIT License
Classifier: Programming Language :: Python :: 3
Classifier: Programming Language :: Python :: 3.10
Classifier: Programming Language :: Python :: 3.8
Classifier: Programming Language :: Python :: 3.9
Requires-Dist: aiohttp (>=3.8.1,<4.0.0)
Requires-Dist: asyncer (>=0.0.1,<0.0.2)
Requires-Dist: boto3 (>=1.20.46,<2.0.0)
Requires-Dist: moto (>=3.0.2,<4.0.0)
Requires-Dist: typing-extensions (>=4.0.1,<5.0.0)
Project-URL: Repository, https://github.com/hemma/py-lambda-simulator
